odoo/addons/base_country_state_translatable/README.rst
odoo/addons/base_country_state_translatable/__init__.py
odoo/addons/base_country_state_translatable/__manifest__.py
odoo/addons/base_country_state_translatable/i18n/base_country_state_translatable.pot
odoo/addons/base_country_state_translatable/i18n/ca.po
odoo/addons/base_country_state_translatable/i18n/da.po
odoo/addons/base_country_state_translatable/i18n/de.po
odoo/addons/base_country_state_translatable/i18n/es.po
odoo/addons/base_country_state_translatable/i18n/fr.po
odoo/addons/base_country_state_translatable/i18n/hr.po
odoo/addons/base_country_state_translatable/i18n/hr_HR.po
odoo/addons/base_country_state_translatable/i18n/it.po
odoo/addons/base_country_state_translatable/i18n/pt_BR.po
odoo/addons/base_country_state_translatable/i18n/sl.po
odoo/addons/base_country_state_translatable/models/__init__.py
odoo/addons/base_country_state_translatable/models/res_country.py
odoo/addons/base_country_state_translatable/readme/CONTRIBUTORS.md
odoo/addons/base_country_state_translatable/readme/DESCRIPTION.md
odoo/addons/base_country_state_translatable/readme/USAGE.md
odoo/addons/base_country_state_translatable/static/description/icon.png
odoo/addons/base_country_state_translatable/static/description/index.html
odoo_addon_base_country_state_translatable-19.0.1.0.0.2.dist-info/METADATA
odoo_addon_base_country_state_translatable-19.0.1.0.0.2.dist-info/WHEEL
odoo_addon_base_country_state_translatable-19.0.1.0.0.2.dist-info/top_level.txt
odoo_addon_base_country_state_translatable-19.0.1.0.0.2.dist-info/RECORD
