Metadata-Version: 2.1
Name: odoo-addon-base_country_state_translatable
Version: 19.0.1.0.0.2
Requires-Dist: odoo==19.0.*
Summary: Translate Country States
Home-page: https://github.com/OCA/partner-contact
License: AGPL-3
Author: initOS GmbH, Odoo Community Association (OCA)
Author-email: support@odoo-community.org
Classifier: Programming Language :: Python
Classifier: Framework :: Odoo
Classifier: Framework :: Odoo :: 19.0
Classifier: License :: OSI Approved :: GNU Affero General Public License v3
